stormglass/__init__.py
stormglass/client.py
stormglass/rate_limiter.py
stormglass/types.py
stormglass-0.1.4.dist-info/LICENSE
stormglass-0.1.4.dist-info/METADATA
stormglass-0.1.4.dist-info/WHEEL
stormglass-0.1.4.dist-info/top_level.txt
stormglass-0.1.4.dist-info/RECORD
