Metadata-Version: 2.1
Name: stormglass
Version: 0.1.4
Summary: Python wrapper for the Storm Glass Global weather API
Home-page: https://github.com/caalle/stormglass-python
Author: Carl Larsson
Author-email: cf@stormglass.io
License: MIT
Keywords: stormglass,weather,marine weather
Platform: UNKNOWN
Classifier: Intended Audience :: Developers
Classifier: Development Status :: 1 - Planning
Classifier: Development Status :: 2 - Pre-Alpha
Classifier: Programming Language :: Python :: 3.8
Requires-Python: >=3.8.*
Requires-Dist: urllib3
Requires-Dist: certifi
